{
  "project_info": {
    "project_number": "714271439485",
    "firebase_url": "https://recipeapp-75eb5-default-rtdb.firebaseio.com",
    "project_id": "recipeapp-75eb5",
    "storage_bucket": "recipeapp-75eb5.firebasestorage.app"
  },
  "client": [
    {
      "client_info": {
        "mobilesdk_app_id": "1:714271439485:android:aab619df01380f2f640f14",
        "android_client_info": {
          "package_name": "com.example.recipeapp"
        }
      },
      "oauth_client": [],
      "api_key": [
        {
          "current_key": "AIzaSyAZcVCfK_-TO6q5rsoKZ5LY9QRqFgyu_rY"
        }
      ],
      "services": {
        "appinvite_service": {
          "other_platform_oauth_client": []
        }
      }
    }
  ],
  "configuration_version": "1"
}